src/__init__.py
src/plotbact.py
src/trackbact.py
trackbact-0.1.0.dist-info/LICENSE
trackbact-0.1.0.dist-info/METADATA
trackbact-0.1.0.dist-info/WHEEL
trackbact-0.1.0.dist-info/entry_points.txt
trackbact-0.1.0.dist-info/top_level.txt
trackbact-0.1.0.dist-info/RECORD
